messente/api/sms/__init__.py
messente/api/sms/constants.py
messente/api/sms/logging.py
messente/api/sms/messente.py
messente/api/sms/api/__init__.py
messente/api/sms/api/api.py
messente/api/sms/api/config.py
messente/api/sms/api/credit.py
messente/api/sms/api/delivery.py
messente/api/sms/api/error.py
messente/api/sms/api/number_verification.py
messente/api/sms/api/pricing.py
messente/api/sms/api/response.py
messente/api/sms/api/sms.py
messente/api/sms/api/utils.py
messente/api/sms/api/verification_widget.py
messente_python-2.0.1.dist-info/LICENSE.txt
messente_python-2.0.1.dist-info/METADATA
messente_python-2.0.1.dist-info/WHEEL
messente_python-2.0.1.dist-info/top_level.txt
messente_python-2.0.1.dist-info/RECORD
