Metadata-Version: 2.1
Name: messente-python
Version: 2.0.1
Summary: Messente SMS API
Home-page: https://github.com/messente/messente-python
Author: Messente
Author-email: messente@messente.com
License: Apache-2.0
Keywords: messente,sms,verification,2FA,pincode
Platform: UNKNOWN
Requires-Python: ~=3.6
Requires-Dist: requests (==2.*)
